{
  "id": 18,
  "title": "Inițiale cuvinte",
  "category": "Șiruri de caractere",
  "timeLimit": 1000,
  "testsCount": 5,
  "description": "Se citește de la tastatură o frază având maximum 100 de caractere, în care cuvintele sunt separate prin câte un spațiu.\n\n**Cerință:** Construiește și afișează un șir ce conține doar primul caracter al fiecăruia dintre cuvintele frazei, în ordinea în care acestea apar în frază.\n\n### Exemplu\n\n**Intrare:**\n```\nAna sustine bacalaureatul la informatica\n```\n\n**Ieșire:**\n```\nAsbli\n```",
  "tips": [
    "Primul caracter al frazei este automat prima inițială",
    "Fiecare caracter de după un spațiu este o inițială",
    "Construiește un șir cu aceste caractere"
  ]
}
